LICENSE.md
README.md
setup.cfg
setup.py
sqladmin_async/__init__.py
sqladmin_async/_menu.py
sqladmin_async/_queries.py
sqladmin_async/_types.py
sqladmin_async/_validators.py
sqladmin_async/ajax.py
sqladmin_async/application.py
sqladmin_async/authentication.py
sqladmin_async/exceptions.py
sqladmin_async/fields.py
sqladmin_async/formatters.py
sqladmin_async/forms.py
sqladmin_async/helpers.py
sqladmin_async/models.py
sqladmin_async/pagination.py
sqladmin_async/py.typed
sqladmin_async/templating.py
sqladmin_async/widgets.py
sqladmin_async.egg-info/PKG-INFO
sqladmin_async.egg-info/SOURCES.txt
sqladmin_async.egg-info/dependency_links.txt
sqladmin_async.egg-info/not-zip-safe
sqladmin_async.egg-info/top_level.txt
sqladmin_async/statics/css/flatpickr.min.css
sqladmin_async/statics/css/fontawesome.min.css
sqladmin_async/statics/css/main.css
sqladmin_async/statics/css/select2.min.css
sqladmin_async/statics/css/tabler.min.css
sqladmin_async/statics/js/bootstrap.min.js
sqladmin_async/statics/js/flatpickr.min.js
sqladmin_async/statics/js/jquery.min.js
sqladmin_async/statics/js/main.js
sqladmin_async/statics/js/popper.min.js
sqladmin_async/statics/js/select2.full.min.js
sqladmin_async/statics/js/tabler.min.js
sqladmin_async/statics/webfonts/fa-brands-400.woff2
sqladmin_async/statics/webfonts/fa-regular-400.woff2
sqladmin_async/statics/webfonts/fa-solid-900.woff2
sqladmin_async/templates/sqladmin/_macros.html
sqladmin_async/templates/sqladmin/base.html
sqladmin_async/templates/sqladmin/create.html
sqladmin_async/templates/sqladmin/details.html
sqladmin_async/templates/sqladmin/edit.html
sqladmin_async/templates/sqladmin/error.html
sqladmin_async/templates/sqladmin/index.html
sqladmin_async/templates/sqladmin/layout.html
sqladmin_async/templates/sqladmin/list.html
sqladmin_async/templates/sqladmin/login.html
sqladmin_async/templates/sqladmin/modals/delete.html
sqladmin_async/templates/sqladmin/modals/details_action_confirmation.html
sqladmin_async/templates/sqladmin/modals/list_action_confirmation.html